canvas_grab/__init__.py
canvas_grab/__main__.py
canvas_grab/config/__init__.py
canvas_grab/config/endpoint.py
canvas_grab/config/organize_mode.py
canvas_grab/configurable.py
canvas_grab/course_filter/__init__.py
canvas_grab/course_filter/all_filter.py
canvas_grab/course_filter/base_filter.py
canvas_grab/course_filter/per_filter.py
canvas_grab/course_filter/term_filter.py
canvas_grab/course_parser.py
canvas_grab/download_file.py
canvas_grab/error.py
canvas_grab/file_filter.py
canvas_grab/get_options.py
canvas_grab/planner.py
canvas_grab/request_batcher.py
canvas_grab/snapshot/__init__.py
canvas_grab/snapshot/canvas_file_snapshot.py
canvas_grab/snapshot/canvas_module_snapshot.py
canvas_grab/snapshot/on_disk_snapshot.py
canvas_grab/snapshot/snapshot.py
canvas_grab/snapshot/snapshot_file.py
canvas_grab/snapshot/snapshot_link.py
canvas_grab/transfer.py
canvas_grab/utils.py
canvas_grab/version.py
canvas_grab-0.1.0.dist-info/entry_points.txt
canvas_grab-0.1.0.dist-info/LICENSE
canvas_grab-0.1.0.dist-info/WHEEL
canvas_grab-0.1.0.dist-info/METADATA
canvas_grab-0.1.0.dist-info/RECORD
