Metadata-Version: 2.1
Name: canvas-grab
Version: 0.1.0
Summary: Downloads all Canvas files to a local directory. Provides GUI for managing the download.[
License: MIT
Author: Alex Chi (skyzh)
Author-email: iskyzh@gmail.com
Requires-Python: >=3.7,<3.11
Classifier: License :: OSI Approved :: MIT License
Classifier: Programming Language :: Python :: 3
Classifier: Programming Language :: Python :: 3.10
Classifier: Programming Language :: Python :: 3.7
Classifier: Programming Language :: Python :: 3.8
Classifier: Programming Language :: Python :: 3.9
Requires-Dist: PySide6 (>=6.4,<7.0)
Requires-Dist: canvasapi (>=3.0,<4.0)
Requires-Dist: colorama (>=0.4,<0.5)
Requires-Dist: jupyter (>=1.0,<2.0)
Requires-Dist: packaging (>=23,<24)
Requires-Dist: questionary (>=1.10,<2.0)
Requires-Dist: retrying (>=1.3,<2.0)
Requires-Dist: termcolor (>=2.2,<3.0)
Requires-Dist: toml (>=0.10,<0.11)
Requires-Dist: tqdm (>=4.64,<5.0)
